LICENSE
MANIFEST.in
Makefile
README.md
requirements.txt
setup.cfg
setup.py
badger_voter_sdk/__init__.py
badger_voter_sdk/aws.py
badger_voter_sdk/cast_vote.py
badger_voter_sdk/constants.py
badger_voter_sdk/discord.py
badger_voter_sdk/json_logger.py
badger_voter_sdk/utils.py
badger_voter_sdk/web3.py
badger_voter_sdk.egg-info/PKG-INFO
badger_voter_sdk.egg-info/SOURCES.txt
badger_voter_sdk.egg-info/dependency_links.txt
badger_voter_sdk.egg-info/requires.txt
badger_voter_sdk.egg-info/top_level.txt
badger_voter_sdk/collectors/__init__.py
badger_voter_sdk/collectors/api_collectors.py
badger_voter_sdk/collectors/data_processors.py
badger_voter_sdk/collectors/snapshot_collectors.py
badger_voter_sdk/collectors/transports.py