Metadata-Version: 2.1
Name: badger-voter-sdk
Version: 0.1.1
Summary: Shared code for badger autovoters
Home-page: https://github.com/Badger-Finance/badger-voter-sdk
Author: SHAKOTN
Author-email: andrii@badger.com
License: MIT
Keywords: badger-voter-sdk
Platform: UNKNOWN
Classifier: License :: OSI Approved :: MIT License
Classifier: Intended Audience :: Developers
Classifier: Programming Language :: Python :: 3
Requires-Python: >=3.7,<4
License-File: LICENSE
